BidiHandler/BidiHandler.py
BidiHandler/__init__.py
BidiHandler-0.0.1.dist-info/METADATA
BidiHandler-0.0.1.dist-info/WHEEL
BidiHandler-0.0.1.dist-info/top_level.txt
BidiHandler-0.0.1.dist-info/RECORD
