Metadata-Version: 2.1
Name: BidiHandler
Version: 0.0.1
Summary: A Python clpackage handling the Arabic base bidirectional text.
Home-page: https://github.com/Hawary13/RTL-BasedBidirectionalTextHandler
Author: Hawary
Author-email: hawary.1311@email.com
License: MIT
Platform: UNKNOWN
Classifier: Programming Language :: Python :: 3
Classifier: License :: OSI Approved :: MIT License
Classifier: Operating System :: OS Independent
